sentry_databricks/daemon.py
sentry_databricks/notebook/__init__.py
sentry_databricks-0.3.1.dist-info/WHEEL
sentry_databricks-0.3.1.dist-info/METADATA
sentry_databricks-0.3.1.dist-info/RECORD
